README.md
setup.py
tap_ringcentral/__init__.py
tap_ringcentral/cache.py
tap_ringcentral/client.py
tap_ringcentral/config.py
tap_ringcentral/state.py
tap_ringcentral.egg-info/PKG-INFO
tap_ringcentral.egg-info/SOURCES.txt
tap_ringcentral.egg-info/dependency_links.txt
tap_ringcentral.egg-info/entry_points.txt
tap_ringcentral.egg-info/requires.txt
tap_ringcentral.egg-info/top_level.txt
tap_ringcentral/schemas/call_log.json
tap_ringcentral/schemas/company_call_log.json
tap_ringcentral/schemas/contacts.json
tap_ringcentral/schemas/messages.json
tap_ringcentral/streams/__init__.py
tap_ringcentral/streams/base.py
tap_ringcentral/streams/call_log.py
tap_ringcentral/streams/company_call_log.py
tap_ringcentral/streams/contacts.py
tap_ringcentral/streams/messages.py